winrpmdepscalc/__init__.py
winrpmdepscalc/cli.py
winrpmdepscalc/config.py
winrpmdepscalc/downloader.py
winrpmdepscalc/metadata_manager.py
winrpmdepscalc/operations.py
winrpmdepscalc/utils.py
winrpmdepscalc-1.0.3.dist-info/licenses/LICENSE
winrpmdepscalc-1.0.3.dist-info/METADATA
winrpmdepscalc-1.0.3.dist-info/WHEEL
winrpmdepscalc-1.0.3.dist-info/entry_points.txt
winrpmdepscalc-1.0.3.dist-info/top_level.txt
winrpmdepscalc-1.0.3.dist-info/RECORD
