Metadata-Version: 2.4
Name: winrpmdepscalc
Version: 1.0.3
Summary: Windows RPM Package Metadata Calculator Tool
Author-email: Maulusck✖Perplexity <maulusck@pm.me>
License-Expression: WTFPL
Project-URL: Home-page, https://github.com/maulusck/winrpmdepscalc
Classifier: Programming Language :: Python :: 3
Classifier: Operating System :: Microsoft :: Windows
Classifier: Operating System :: POSIX :: Linux
Requires-Python: >=3.7
License-File: LICENSE
Requires-Dist: requests
Requires-Dist: PyYAML
Requires-Dist: tqdm
Requires-Dist: urllib3
Provides-Extra: dev
Requires-Dist: black; extra == "dev"
Requires-Dist: isort; extra == "dev"
Dynamic: license-file
